dsplib/__init__.py
dsplib/circular_buffer.py
dsplib/window.py
dsplib/scale/__init__.py
dsplib/scale/numpy.py
dsplib/scale/python.py
dsplib-0.10.1.dist-info/METADATA
dsplib-0.10.1.dist-info/WHEEL
dsplib-0.10.1.dist-info/top_level.txt
dsplib-0.10.1.dist-info/RECORD
